clustery
