Metadata-Version: 2.1
Name: Clustery
Version: 1.5
Summary: Database system that makes life way easier than SQL.
Author: JKlijzing
Author-email: jklijzing@shrp.tv
Keywords: clustery,db,database
Classifier: Development Status :: 5 - Production/Stable
Classifier: Intended Audience :: Developers
Classifier: Topic :: Database :: Database Engines/Servers
Classifier: Programming Language :: Python :: 3.8
Classifier: Programming Language :: Python :: 3.9
Classifier: Programming Language :: Python :: 3.10
Classifier: Programming Language :: Python :: 3.11
Classifier: Programming Language :: Python :: 3.12
